shadowlegion/__init__.py
shadowlegion/core.py
shadowlegion/utils.py
shadowlegion/__metadata__/DISCLIAIMER.md
shadowlegion/__metadata__/LICENSE
shadowlegion/__metadata__/README.md
shadowlegion/__metadata__/__init__.py
shadowlegion/__metadata__/requirements.txt
shadowlegion-0.0.7.dist-info/METADATA
shadowlegion-0.0.7.dist-info/WHEEL
shadowlegion-0.0.7.dist-info/top_level.txt
shadowlegion-0.0.7.dist-info/RECORD
